pyjvm
pyjvm_gui
pyjvm_util
pyjvmgui
