Metadata-Version: 2.1
Name: pyjvmgui
Version: 1.3.9
Summary: A GUI for the PyJVM
Home-page: https://github.com/MatevzFa/pyjvm
Author: matevz
Author-email: mf6422@student.uni-lj.si
License: GPL-3.0
Platform: UNKNOWN
